pyotr/client/__init__.py
pyotr/server/__init__.py
pyotr/utils.py
pyotr/validation/__init__.py
pyotr/validation/requests/__init__.py
pyotr/validation/requests/client.py
pyotr/validation/requests/starlette.py
pyotr/validation/responses/__init__.py
pyotr/validation/responses/client.py
pyotr/validation/responses/starlette.py
pyotr-0.8.0.dist-info/LICENSE
pyotr-0.8.0.dist-info/WHEEL
pyotr-0.8.0.dist-info/METADATA
pyotr-0.8.0.dist-info/RECORD
