Metadata-Version: 2.1
Name: pyotr
Version: 0.8.0
Summary: Python OpenAPI-to-REST (and back) framework 
Home-page: https://pyotr.readthedocs.io
License: MIT
Author: Berislav Lopac
Author-email: berislav@lopac.net
Requires-Python: >=3.8,<4.0
Classifier: License :: OSI Approved :: MIT License
Classifier: Programming Language :: Python :: 3
Classifier: Programming Language :: Python :: 3.10
Classifier: Programming Language :: Python :: 3.8
Classifier: Programming Language :: Python :: 3.9
Provides-Extra: uvicorn
Requires-Dist: PyYAML (>=6.0,<7.0)
Requires-Dist: httpx (>=0.22.0,<0.23.0)
Requires-Dist: openapi-core (>=0.14.2,<0.15.0)
Requires-Dist: starlette (>=0.19.0,<0.20.0)
Requires-Dist: stringcase (>=1.2.0,<2.0.0)
Requires-Dist: typing-extensions (>=4.1.1,<5.0.0)
Requires-Dist: uvicorn (>=0.17.6,<0.18.0); extra == "uvicorn"
Project-URL: Repository, https://github.com/berislavlopac/pyotr
